{"*":{"core":{"audioBeep":false,"disabledPackages":["autocomplete-plus"],"projectHome":"/Users/dawsonbotsford/code","themes":["one-dark-ui","cobalt2-syntax"]},"editor":{"fontFamily":"Operator Mono","lineHeight":1.1,"showIndentGuide":true,"showInvisibles":true},"exception-reporting":{"userId":"0162869f-52b3-9ff3-432a-840d5e10ef34"},"pigments":{"markerType":"native-outline"},"sync-settings":{"_analyticsUserId":"b89f0295-f0a5-4cde-80ba-d879e95eaa43","_lastBackupHash":"214a13be0cc314e77d2fcd03468cc50229bab41d","gistId":"324b1756618c44dc1ca0","personalAccessToken":"58be7484384a4430110906b035980938201d9eca"},"terminal-status":{"WindowHeight":100},"tree-view":{"hideIgnoredNames":true},"welcome":{"showOnStartup":false}}}